{
  "name": "menuOnScroll",
  "title": "jQuery menuOnScroll",
  "description": "A jQuery plugin that allows you to auto update your navigation menu automatically when you scroll",
  "keywords": [
    "\"jquery\"",
    "\"plugin\"",
    "\"menu",
    "\"navigation",
    "scroll\"",
    "auto"
  ],
  "version": "0.1.0",
  "author": {
    "name": "Khoa Pham",
    "email": "khoa.pham@me.com",
    "url": "https://github.com/pmkhoa"
  },
  "licenses": [
    {
      "type": "MIT"
    }
  ],
  "homepage": "http://menuonscroll.com",
  "dependencies": {
    "jquery": ">=1.8"
  }
}
